openinference/instrumentation/portkey/__init__.py
openinference/instrumentation/portkey/_request_attributes_extractor.py
openinference/instrumentation/portkey/_response_attributes_extractor.py
openinference/instrumentation/portkey/_utils.py
openinference/instrumentation/portkey/_with_span.py
openinference/instrumentation/portkey/_wrappers.py
openinference/instrumentation/portkey/version.py
openinference_instrumentation_portkey-0.1.7.dist-info/METADATA
openinference_instrumentation_portkey-0.1.7.dist-info/WHEEL
openinference_instrumentation_portkey-0.1.7.dist-info/entry_points.txt
openinference_instrumentation_portkey-0.1.7.dist-info/RECORD
